wheelbin/PythonFile.py
wheelbin/TemporaryDirectory.py
wheelbin/WheelFile.py
wheelbin/ZipArchive.py
wheelbin/__init__.py
wheelbin/__main__.py
wheelbin-1.4.1.dist-info/LICENSE
wheelbin-1.4.1.dist-info/METADATA
wheelbin-1.4.1.dist-info/WHEEL
wheelbin-1.4.1.dist-info/entry_points.txt
wheelbin-1.4.1.dist-info/top_level.txt
wheelbin-1.4.1.dist-info/RECORD
